ehentai/__init__.py
ehentai/__version__.py
ehentai/api.py
ehentai/conf.py
ehentai/connect.py
ehentai/eh.py
ehentai/fetch.py
ehentai/utils.py
ehentai-0.2.4.dist-info/licenses/LICENSE
ehentai-0.2.4.dist-info/licenses/NOTICE
ehentai-0.2.4.dist-info/METADATA
ehentai-0.2.4.dist-info/WHEEL
ehentai-0.2.4.dist-info/entry_points.txt
ehentai-0.2.4.dist-info/top_level.txt
ehentai-0.2.4.dist-info/RECORD
